csepy/__init__.py
csepy/csepy.py
csepy/PublicFunctions/__init__.py
csepy/PublicFunctions/CommandInterface/ICommand.py
csepy/PublicFunctions/CommandInterface/__init__.py
csepy/PublicFunctions/LanguageCommand/RunScriptCommand.py
csepy/PublicFunctions/LanguageCommand/__init__.py
csepy/PublicFunctions/ShellCommands/EchoCommand.py
csepy/PublicFunctions/ShellCommands/__init__.py
csepy/PublicFunctions/ShellCommands/ShellCommandExecutor/ShellCommandExecutor.py
csepy/PublicFunctions/ShellCommands/ShellCommandExecutor/__init__.py
csepy/PublicFunctions/SupportCommands/HelpCommand.py
csepy/PublicFunctions/SupportCommands/__init__.py
csepy/PublicFunctions/SystemCommands/AsyncCommand.py
csepy/PublicFunctions/SystemCommands/LoopCommand.py
csepy/PublicFunctions/SystemCommands/WaitCommand.py
csepy/PublicFunctions/SystemCommands/__init__.py
csepy/PublicFunctions/SystemCommands/ForEachCommands/AsyncForEachCommand.py
csepy/PublicFunctions/SystemCommands/ForEachCommands/ForEachCommand.py
csepy/PublicFunctions/SystemCommands/ForEachCommands/ForEachLogic.py
csepy/PublicFunctions/SystemCommands/ForEachCommands/__init__.py
csepy/System/Regex.py
csepy/System/__init__.py
csepy/System/CommandQueue/CommandQueue.py
csepy/System/CommandQueue/CommandQueueFactory.py
csepy/System/CommandQueue/__init__.py
csepy/System/Configurations/ConfigArchivist.py
csepy/System/Configurations/SystemConfig.py
csepy/System/Configurations/__init__.py
csepy/System/EndpointMap/EndpointMapper.py
csepy/System/EndpointMap/__init__.py
csepy/System/EnqueueAndRun/EnqueueAndRun.py
csepy/System/EnqueueAndRun/__init__.py
csepy/System/FileSystem/FileSystem.py
csepy/System/FileSystem/__init__.py
csepy/System/Language/SystemLanguage.py
csepy/System/Language/__init__.py
csepy/System/Logger/Colors.py
csepy/System/Logger/Logger.py
csepy/System/Logger/LoggerFactory.py
csepy/System/Logger/__init__.py
csepy/System/Models/__init__.py
csepy/System/Models/Context/Context.py
csepy/System/Models/Context/ContextFactory.py
csepy-0.0.1.2.dist-info/LICENSE
csepy-0.0.1.2.dist-info/METADATA
csepy-0.0.1.2.dist-info/WHEEL
csepy-0.0.1.2.dist-info/top_level.txt
csepy-0.0.1.2.dist-info/RECORD
