Metadata-Version: 2.1
Name: csepy
Version: 0.0.1.2
Summary: A python command service engine package
Home-page: https://github.com/csepy/csepy
Author: Yuval Feldman
Author-email: csepyproject@gmail.com
License: UNKNOWN
Platform: UNKNOWN
Classifier: Programming Language :: Python :: 3
Classifier: License :: OSI Approved :: MIT License
Classifier: Operating System :: OS Independent
